odoo/addons/html_fields_document_layout_configuration/README.rst
odoo/addons/html_fields_document_layout_configuration/__init__.py
odoo/addons/html_fields_document_layout_configuration/__manifest__.py
odoo/addons/html_fields_document_layout_configuration/static/description/icon.png
odoo/addons/html_fields_document_layout_configuration/views/view_base_document_layout.xml
odoo_addon_html_fields_document_layout_configuration-16.0.1.0.0.1.dist-info/METADATA
odoo_addon_html_fields_document_layout_configuration-16.0.1.0.0.1.dist-info/WHEEL
odoo_addon_html_fields_document_layout_configuration-16.0.1.0.0.1.dist-info/top_level.txt
odoo_addon_html_fields_document_layout_configuration-16.0.1.0.0.1.dist-info/RECORD
