Metadata-Version: 2.1
Name: odoo-addon-html_fields_document_layout_configuration
Version: 16.0.1.0.0.1
Requires-Python: >=3.10
Requires-Dist: odoo>=16.0a,<16.1dev
Summary: Html fields in document layout configuration
Home-page: https://github.com/sygel-technology/sy-server-tools
License: AGPL-3
Author: Sygel, Odoo Community Association (OCA)
Author-email: support@odoo-community.org
Classifier: Programming Language :: Python
Classifier: Framework :: Odoo
Classifier: Framework :: Odoo :: 16.0
Classifier: License :: OSI Approved :: GNU Affero General Public License v3
